cool_login_banner/__init__.py
cool_login_banner/banner_setter.py
cool_login_banner/engines.py
cool_login_banner-0.1.2.dist-info/METADATA
cool_login_banner-0.1.2.dist-info/WHEEL
cool_login_banner-0.1.2.dist-info/RECORD
