Metadata-Version: 2.1
Name: cool-login-banner
Version: 0.1.2
Summary: Easy and quick set interesting linux login banner.
Author: telecomshy
Author-email: telecomshy@126.com
Requires-Python: >=3.12,<4.0
Classifier: Programming Language :: Python :: 3
Requires-Dist: cowsay (>=6.1,<7.0)
Requires-Dist: fabric (>=3.2.2,<4.0.0)
Requires-Dist: invoke (>=2.2.0,<3.0.0)
Requires-Dist: pyfiglet (>=1.0.2,<2.0.0)
Requires-Dist: pytest (>=8.1.1,<9.0.0)
Requires-Dist: termcolor (>=2.4.0,<3.0.0)
